topsis_nikhil_102218082/__init__.py
topsis_nikhil_102218082/topsis.py
topsis_nikhil_102218082-0.1.dist-info/LICENSE
topsis_nikhil_102218082-0.1.dist-info/METADATA
topsis_nikhil_102218082-0.1.dist-info/WHEEL
topsis_nikhil_102218082-0.1.dist-info/entry_points.txt
topsis_nikhil_102218082-0.1.dist-info/top_level.txt
topsis_nikhil_102218082-0.1.dist-info/RECORD
